setup.cfg
setup.py
dg_alchemy_integration.egg-info/PKG-INFO
dg_alchemy_integration.egg-info/SOURCES.txt
dg_alchemy_integration.egg-info/dependency_links.txt
dg_alchemy_integration.egg-info/entry_points.txt
dg_alchemy_integration.egg-info/requires.txt
dg_alchemy_integration.egg-info/top_level.txt
intellij/__init__.py
intellij/alchemy/__init__.py
intellij/alchemy/dgapi.py
intellij/alchemy/dgapi_connector.py
intellij/alchemy/requirements.py
test/test.py
test/test_suite.py