Metadata-Version: 1.0
Name: dg-alchemy-integration
Version: 0.0.2.dev0
Summary: Implementation of SQLAlchemy API for DataGrip connection
Home-page: UNKNOWN
Author: Alexander Kass
Author-email: UNKNOWN
License: MIT
Keywords: IntelliJ IDEA DataGrip PhpStorm PyCharm GoLand
Platform: UNKNOWN
